erax_vl_7b_v1/__init__.py
erax_vl_7b_v1/erax_api_lib.py
erax_vl_7b_v1/prompts.py
erax_vl_7b_v1/utils.py
erax_vl_7b_v1-0.1.1.dist-info/LICENSE
erax_vl_7b_v1-0.1.1.dist-info/METADATA
erax_vl_7b_v1-0.1.1.dist-info/WHEEL
erax_vl_7b_v1-0.1.1.dist-info/top_level.txt
erax_vl_7b_v1-0.1.1.dist-info/RECORD
