Metadata-Version: 2.1
Name: erax-vl-7b-v1
Version: 0.1.1
Summary: EraX-VL-7B-V1 - A multimodal vision-language model based on Qwen2-VL-7B architecture.
Home-page: https://github.com/EraX-JS-Company/erax-vl-7b-v1
Author: EraX
Author-email: nguyen@erax.ai
License: Apache License 2.0
Classifier: Development Status :: 3 - Alpha
Classifier: Programming Language :: Python :: 3
Classifier: License :: OSI Approved :: Apache Software License
Classifier: Operating System :: OS Independent
Classifier: Topic :: Scientific/Engineering :: Artificial Intelligence
Requires-Python: >=3.6
License-File: LICENSE
Requires-Dist: json-repair
Requires-Dist: numpy
Requires-Dist: matplotlib
Requires-Dist: tqdm
Requires-Dist: pillow
Requires-Dist: PyMuPDF
Requires-Dist: opencv-python
Requires-Dist: python-dotenv
Requires-Dist: requests
Requires-Dist: regex
